modern_robotics/__init__.py
modern_robotics/__version__.py
modern_robotics/core.py
modern_robotics-1.1.1.dist-info/METADATA
modern_robotics-1.1.1.dist-info/WHEEL
modern_robotics-1.1.1.dist-info/top_level.txt
modern_robotics-1.1.1.dist-info/RECORD
